[
  {
    "word": {
      "text": "航空券",
      "transliterations": "こうくうけん",
      "part_of_speech": "Noun",
      "meaning": "airline ticket",
      "sound": "https://assets2.iknow.jp/assets/legacy/JLL/audio/Int/JW03613A.mp3"
    },
    "sentences": [
      {
        "text": "電話で<b>航空券</b>を予約しました。",
        "transliterations": "でんわ で <b>こうくうけん</b> を よやく しました。",
        "meaning": "I booked an airline ticket by phone.",
        "sound": "https://assets0.iknow.jp/assets/legacy/JLL/audio/Int/JS03613A.mp3"
      }
    ]
  },
  {
    "word": {
      "text": "栓抜き",
      "transliterations": "せんぬき",
      "part_of_speech": "Noun",
      "meaning": "bottle opener",
      "sound": "https://assets3.iknow.jp/assets/legacy/JLL/audio/Int/JW03697A.mp3"
    },
    "sentences": [
      {
        "text": "<b>栓抜き</b>はどこですか。",
        "transliterations": "<b>せん ぬき</b>  は どこ です か。",
        "meaning": "Where's the bottle opener?",
        "sound": "https://assets1.iknow.jp/assets/legacy/JLL/audio/Int/JS03697A.mp3"
      }
    ]
  },
  {
    "word": {
      "text": "とがる",
      "transliterations": "とがる",
      "part_of_speech": "Verb",
      "meaning": "be sharp",
      "sound": "https://assets2.iknow.jp/assets/legacy/JLL/audio/Int/JW03774A.mp3"
    },
    "sentences": [
      {
        "text": "この鉛筆は<b>とがって</b>いますね。",
        "transliterations": "この えんぴつ は <b>とがって</b> います ね。",
        "meaning": "This pencil is sharp.",
        "sound": "https://assets0.iknow.jp/assets/legacy/JLL/audio/Int/JS03774A.mp3"
      }
    ]
  },
  {
    "word": {
      "text": "臭う",
      "transliterations": "におう",
      "part_of_speech": "Verb",
      "meaning": "stink (unpleasant)",
      "sound": "https://assets2.iknow.jp/assets/legacy/JLL/audio/Int/JW03795A.mp3"
    },
    "sentences": [
      {
        "text": "流しが<b>臭う</b>のできれいにしたよ。",
        "transliterations": "ながし が <b>におう</b> ので きれい に した よ。",
        "meaning": "I cleaned the sink because it stank.",
        "sound": "https://assets0.iknow.jp/assets/legacy/JLL/audio/Int/JS03795A.mp3"
      }
    ]
  },
  {
    "word": {
      "text": "のんき",
      "transliterations": "のんき",
      "part_of_speech": "Adjectival Noun",
      "meaning": "carefree, happy-go-lucky",
      "sound": "https://assets0.iknow.jp/assets/legacy/JLL/audio/Int/JW03813A.mp3"
    },
    "sentences": [
      {
        "text": "彼はずいぶん<b>のんき</b>なやつだ。",
        "transliterations": "かれ は ずいぶん <b>のんき</b>な やつ だ。",
        "meaning": "He's a very happy-go-lucky guy.",
        "sound": "https://assets2.iknow.jp/assets/legacy/JLL/audio/Int/JS03813A.mp3"
      }
    ]
  },
  {
    "word": {
      "text": "はしご",
      "transliterations": "はしご",
      "part_of_speech": "Noun",
      "meaning": "ladder",
      "sound": "https://assets0.iknow.jp/assets/legacy/JLL/audio/Int/JW03822A.mp3"
    },
    "sentences": [
      {
        "text": "<b>はしご</b>を使って屋根に上りました。",
        "transliterations": "<b>はしご</b> を つかって やね に のぼりました。",
        "meaning": "I went up to the roof on a ladder.",
        "sound": "https://assets2.iknow.jp/assets/legacy/JLL/audio/Int/JS03822A.mp3"
      }
    ]
  },
  {
    "word": {
      "text": "引っ掛ける",
      "transliterations": "ひっかける",
      "part_of_speech": "Verb",
      "meaning": "hook (something) on",
      "sound": "https://assets2.iknow.jp/assets/legacy/JLL/audio/Int/JW03845A.mp3"
    },
    "sentences": [
      {
        "text": "その選手はハードルに足を<b>引っ掛けた</b>んだ。",
        "transliterations": "その せんしゅ は ハードル に あし を <b>ひっかけた</b> ん だ。",
        "meaning": "The athlete caught his foot on the hurdle.",
        "sound": "https://assets0.iknow.jp/assets/legacy/JLL/audio/Int/JS03845A.mp3"
      }
    ]
  },
  {
    "word": {
      "text": "麓",
      "transliterations": "ふもと",
      "part_of_speech": "Noun",
      "meaning": "foot of the mountain",
      "sound": "https://assets1.iknow.jp/assets/legacy/JLL/audio/Int/JW03859A.mp3"
    },
    "sentences": [
      {
        "text": "彼は山の<b>麓</b>に住んでいるよ。",
        "transliterations": "かれ は やま の <b>ふもと</b> に すんで いる よ。",
        "meaning": "He lives at the foot of a mountain.",
        "sound": "https://assets3.iknow.jp/assets/legacy/JLL/audio/Int/JS03859A.mp3"
      }
    ]
  },
  {
    "word": {
      "text": "ほうき",
      "transliterations": "ほうき",
      "part_of_speech": "Noun",
      "meaning": "broom",
      "sound": "https://assets0.iknow.jp/assets/legacy/JLL/audio/Int/JW03870A.mp3"
    },
    "sentences": [
      {
        "text": "<b>ほうき</b>で庭を掃除しました。",
        "transliterations": "<b>ほうき</b> で にわ を そうじ しました。",
        "meaning": "I cleaned up the yard with a broom.",
        "sound": "https://assets2.iknow.jp/assets/legacy/JLL/audio/Int/JS03870A.mp3"
      }
    ]
  },
  {
    "word": {
      "text": "微笑む",
      "transliterations": "ほほえむ",
      "part_of_speech": "Verb",
      "meaning": "smile",
      "sound": "https://assets0.iknow.jp/assets/legacy/JLL/audio/Int/JW03877A.mp3"
    },
    "sentences": [
      {
        "text": "彼女は私に<b>微笑んだ</b>よ。",
        "transliterations": "かのじょ は わたし に <b>ほほえんだ</b> よ。",
        "meaning": "She smiled at me.",
        "sound": "https://assets2.iknow.jp/assets/legacy/JLL/audio/Int/JS03877A.mp3"
      }
    ]
  },
  {
    "word": {
      "text": "真似",
      "transliterations": "まね",
      "part_of_speech": "Verbal Noun",
      "meaning": "imitation, mimicry",
      "sound": "https://assets0.iknow.jp/assets/legacy/JLL/audio/Int/JW03891A.mp3"
    },
    "sentences": [
      {
        "text": "娘はよく私の<b>真似</b>をします。",
        "transliterations": "むすめ は よく わたし の <b>まね</b> を します。",
        "meaning": "My daughter often mimicks me.",
        "sound": "https://assets2.iknow.jp/assets/legacy/JLL/audio/Int/JS03891A.mp3"
      }
    ]
  },
  {
    "word": {
      "text": "儲かる",
      "transliterations": "もうかる",
      "part_of_speech": "Verb",
      "meaning": "be profitable, pay its way",
      "sound": "https://assets3.iknow.jp/assets/legacy/JLL/audio/Int/JW03923A.mp3"
    },
    "sentences": [
      {
        "text": "彼の商売は<b>儲かって</b>いるらしいね。",
        "transliterations": "かれ の しょうばい は <b>もうかって</b> いる らしい ね。",
        "meaning": "His business seems profitable.",
        "sound": "https://assets1.iknow.jp/assets/legacy/JLL/audio/Int/JS03923A.mp3"
      }
    ]
  },
  {
    "word": {
      "text": "レクリエーション",
      "transliterations": "レクリエーション",
      "part_of_speech": "Noun",
      "meaning": "recreation",
      "sound": "https://assets3.iknow.jp/assets/legacy/JLL/audio/Int/JW03966A.mp3"
    },
    "sentences": [
      {
        "text": "町内会の<b>レクリエーション</b>に参加したの。",
        "transliterations": "ちょうない かい の <b>レクリエーション</b> に さんか した の。",
        "meaning": "I took part in the recreational activities organized by the neighborhood association.",
        "sound": "https://assets1.iknow.jp/assets/legacy/JLL/audio/Int/JS03966A.mp3"
      }
    ]
  },
  {
    "word": {
      "text": "ろうそく",
      "transliterations": "ろうそく",
      "part_of_speech": "Noun",
      "meaning": "candle",
      "sound": "https://assets3.iknow.jp/assets/legacy/JLL/audio/Int/JW03968A.mp3"
    },
    "sentences": [
      {
        "text": "バースデーケーキに<b>ろうそく</b>を立てました。",
        "transliterations": "バースデー ケーキ に <b>ろうそく</b> を たてました。",
        "meaning": "We put candles on the birthday cake.",
        "sound": "https://assets1.iknow.jp/assets/legacy/JLL/audio/Int/JS03968A.mp3"
      }
    ]
  },
  {
    "word": {
      "text": "生き生きと",
      "transliterations": "いきいきと",
      "part_of_speech": "Adverb",
      "meaning": "lively, vigorously",
      "sound": "https://assets2.iknow.jp/assets/legacy/JLL/audio/Int/JW03981A.mp3"
    },
    "sentences": [
      {
        "text": "子供たちが<b>生き生きと</b>遊んでいるね。",
        "transliterations": "こども たち が <b>いきいき と</b> あそんで いる ね。",
        "meaning": "The kids are playing with full spirit.",
        "sound": "https://assets0.iknow.jp/assets/legacy/JLL/audio/Int/JS03981A.mp3"
      }
    ]
  },
  {
    "word": {
      "text": "速達便",
      "transliterations": "そくたつびん",
      "part_of_speech": "Noun",
      "meaning": "special delivery mail, express mail",
      "sound": "https://assets2.iknow.jp/assets/legacy/JLL/audio/Int/JW03988A.mp3"
    },
    "sentences": [
      {
        "text": "<b>速達便</b>なら明日の午前中に届きます。",
        "transliterations": "<b>そくたつ びん</b> なら あした の ごぜん ちゅう に とどきます。",
        "meaning": "It will arrive tomorrow morning if you send it by express mail.",
        "sound": "https://assets0.iknow.jp/assets/legacy/JLL/audio/Int/JS03988A.mp3"
      }
    ]
  },
  {
    "word": {
      "text": "必死に",
      "transliterations": "ひっしに",
      "part_of_speech": "Adverb",
      "meaning": "desperately",
      "sound": "https://assets0.iknow.jp/assets/legacy/JLL/audio/Int/JW03995A.mp3"
    },
    "sentences": [
      {
        "text": "<b>必死に</b>単語を暗記したよ。",
        "transliterations": "<b>ひっし</b> に たんご を あんき した よ。",
        "meaning": "I struggled to memorize the words.",
        "sound": "https://assets2.iknow.jp/assets/legacy/JLL/audio/Int/JS03995A.mp3"
      }
    ]
  },
  {
    "word": {
      "text": "上がる",
      "transliterations": "あがる",
      "part_of_speech": "Verb",
      "meaning": "eat, drink (honorific)",
      "sound": "https://assets3.iknow.jp/assets/legacy/JLL/audio/Int/JW00006A.mp3"
    },
    "sentences": [
      {
        "text": "冷めないうちにどうぞお<b>上がり</b>ください。",
        "transliterations": "さめない うち に どうぞ お<b>あがり</b> ください。",
        "meaning": "Please eat it while it's still hot.",
        "sound": "https://assets1.iknow.jp/assets/legacy/JLL/audio/Int/JS00006A.mp3"
      }
    ]
  },
  {
    "word": {
      "text": "荒い",
      "transliterations": "あらい",
      "part_of_speech": "Adjective",
      "meaning": "harsh, rough",
      "sound": "https://assets0.iknow.jp/assets/legacy/JLL/audio/Int/JW01828A.mp3"
    },
    "sentences": [
      {
        "text": "うちの犬は気が<b>荒い</b>。",
        "transliterations": "うち の いぬ は き が <b>あらい</b>。",
        "meaning": "Our dog is bad-tempered.",
        "sound": "https://assets2.iknow.jp/assets/legacy/JLL/audio/Int/JS01828A.mp3"
      }
    ]
  },
  {
    "word": {
      "text": "注ぐ",
      "transliterations": "そそぐ",
      "part_of_speech": "Verb",
      "meaning": "pour into (liquid)",
      "sound": "https://assets1.iknow.jp/assets/legacy/JLL/audio/Int/JW02008A.mp3"
    },
    "sentences": [
      {
        "text": "みんなのグラスにジュースを<b>注いだ</b>よ。",
        "transliterations": "みんな の グラス に ジュース を <b>そそいだ</b> よ。",
        "meaning": "I poured juice into everyone's glass.",
        "sound": "https://assets3.iknow.jp/assets/legacy/JLL/audio/Int/JS02008A.mp3"
      }
    ]
  },
  {
    "word": {
      "text": "流行",
      "transliterations": "りゅうこう",
      "part_of_speech": "Verbal Noun",
      "meaning": "fashion, trend",
      "sound": "https://assets3.iknow.jp/assets/legacy/JLL/audio/Int/JW03961A.mp3"
    },
    "sentences": [
      {
        "text": "このスタイルは今年の<b>流行</b>です。",
        "transliterations": "この スタイル は ことし の <b>りゅうこう</b> です。",
        "meaning": "This style is in fashion this year.",
        "sound": "https://assets1.iknow.jp/assets/legacy/JLL/audio/Int/JS03961A.mp3"
      }
    ]
  },
  {
    "word": {
      "text": "額",
      "transliterations": "ひたい",
      "part_of_speech": "Noun",
      "meaning": "forehead",
      "sound": "https://assets2.iknow.jp/assets/legacy/JLL/audio/Int/JW00095A.mp3"
    },
    "sentences": [
      {
        "text": "<b>額</b>に汗をかいたよ。",
        "transliterations": "<b>ひたい</b> に あせ を かいた よ。",
        "meaning": "My forehead is covered in sweat.",
        "sound": "https://assets0.iknow.jp/assets/legacy/JLL/audio/Int/JS00095A.mp3"
      }
    ]
  },
  {
    "word": {
      "text": "一種",
      "transliterations": "いっしゅ",
      "part_of_speech": "Adverb",
      "meaning": "sort of, almost",
      "sound": "https://assets1.iknow.jp/assets/legacy/JLL/audio/Int/JW00296A.mp3"
    },
    "sentences": [
      {
        "text": "これは<b>一種</b>独特の味がするね。",
        "transliterations": "これ は <b>いっしゅ</b> どくとく の あじ が する ね。",
        "meaning": "This has an unusual sort of taste.",
        "sound": "https://assets3.iknow.jp/assets/legacy/JLL/audio/Int/JS00296A.mp3"
      }
    ]
  },
  {
    "word": {
      "text": "抱く",
      "transliterations": "だく",
      "part_of_speech": "Verb",
      "meaning": "hug, hold",
      "sound": "https://assets0.iknow.jp/assets/legacy/JLL/audio/Int/JW00618A.mp3"
    },
    "sentences": [
      {
        "text": "祖母がうちの猫を<b>抱いて</b>いるわよ。",
        "transliterations": "そぼ が うち の ねこ を <b>だいて</b> いる わ よ。",
        "meaning": "Grandma is holding our cat.",
        "sound": "https://assets2.iknow.jp/assets/legacy/JLL/audio/Int/JS00618A.mp3?1220179334"
      }
    ]
  },
  {
    "word": {
      "text": "柄",
      "transliterations": "がら",
      "part_of_speech": "Noun",
      "meaning": "pattern, print",
      "sound": "https://assets2.iknow.jp/assets/legacy/JLL/audio/Int/JW02513A.mp3"
    },
    "sentences": [
      {
        "text": "彼は犬の<b>柄</b>のTシャツを着ているよ。",
        "transliterations": "かれ は いぬ の <b>がら</b> の ティーシャツ を きて いる よ。",
        "meaning": "He's wearing a T-shirt with a dog print on it.",
        "sound": "https://assets0.iknow.jp/assets/legacy/JLL/audio/Int/JS02513A.mp3"
      }
    ]
  },
  {
    "word": {
      "text": "上",
      "transliterations": "じょう",
      "part_of_speech": "Noun",
      "meaning": "upper, superior",
      "sound": "https://assets0.iknow.jp/assets/legacy/JLL/audio/Int/JW03663A.mp3"
    },
    "sentences": [
      {
        "text": "握り寿司の<b>上</b>を注文したよ。",
        "transliterations": "にぎりずし の <b>じょう</b> を ちゅうもん した よ。",
        "meaning": "I ordered the higher-priced sushi.",
        "sound": "https://assets2.iknow.jp/assets/legacy/JLL/audio/Int/JS03663A.mp3"
      }
    ]
  },
  {
    "word": {
      "text": "下",
      "transliterations": "げ",
      "part_of_speech": "Noun",
      "meaning": "lower, bottom",
      "sound": "https://assets1.iknow.jp/assets/legacy/JLL/audio/Int/JW03608A.mp3"
    },
    "sentences": [
      {
        "text": "彼女の成績は上の<b>下</b>です。",
        "transliterations": "かのじょ の せいせき は じょう の <b>げ</b> です。",
        "meaning": "Her grades are ranked at the bottom of the top group.",
        "sound": "https://assets3.iknow.jp/assets/legacy/JLL/audio/Int/JS03608A.mp3"
      }
    ]
  },
  {
    "word": {
      "text": "盆",
      "transliterations": "ぼん",
      "part_of_speech": "Noun",
      "meaning": "tray",
      "sound": "https://assets1.iknow.jp/assets/legacy/JLL/audio/Int/JW03880A.mp3"
    },
    "sentences": [
      {
        "text": "母が料理をお<b>盆</b>に乗せたの。",
        "transliterations": "はは が りょうり を お<b>ぼん</b> に のせた の。",
        "meaning": "My mother put the dishes on a tray.",
        "sound": "https://assets3.iknow.jp/assets/legacy/JLL/audio/Int/JS03880A.mp3"
      }
    ]
  },
  {
    "word": {
      "text": "逆さま",
      "transliterations": "さかさま",
      "part_of_speech": "Adjectival Noun",
      "meaning": "upside-down, reverse",
      "sound": "https://assets0.iknow.jp/assets/legacy/JLL/audio/Int/JW03444A.mp3"
    },
    "sentences": [
      {
        "text": "それじゃあ上と下が<b>逆さま</b>だよ。",
        "transliterations": "それじゃあ うえ と した が <b>さかさま</b> だ よ。",
        "meaning": "You need to turn it upside down.",
        "sound": "https://assets2.iknow.jp/assets/legacy/JLL/audio/Int/JS03444A.mp3"
      }
    ]
  },
  {
    "word": {
      "text": "割合に",
      "transliterations": "わりあいに",
      "part_of_speech": "Adverb",
      "meaning": "relatively, rather",
      "sound": "https://assets2.iknow.jp/assets/legacy/JLL/audio/Int/JW04000A.mp3"
    },
    "sentences": [
      {
        "text": "今回のテストは<b>割合に</b>簡単でした。",
        "transliterations": "こんかい の テスト は <b>わりあい に</b> かんたん でした。",
        "meaning": "The test was relatively easy this time.",
        "sound": "https://assets0.iknow.jp/assets/legacy/JLL/audio/Int/JS04000A.mp3"
      }
    ]
  },
  {
    "word": {
      "text": "次々に",
      "transliterations": "つぎつぎに",
      "part_of_speech": "Adverb",
      "meaning": "one after another, in succession",
      "sound": "https://assets2.iknow.jp/assets/legacy/JLL/audio/Int/JW00498A.mp3"
    },
    "sentences": [
      {
        "text": "走者が<b>次々 に</b>ゴールしました。",
        "transliterations": "そうしゃ が <b>つぎつぎ に</b> ゴール しました。",
        "meaning": "The runners reached the goal one after another.",
        "sound": "https://assets0.iknow.jp/assets/legacy/JLL/audio/Int/JS00498A.mp3"
      }
    ]
  },
  {
    "word": {
      "text": "罰する",
      "transliterations": "ばっする",
      "part_of_speech": "Verb",
      "meaning": "punish, penalize",
      "sound": "https://assets3.iknow.jp/assets/legacy/JLL/audio/Int/JW03380A.mp3"
    },
    "sentences": [
      {
        "text": "彼は違法駐車で<b>罰せられた</b>んだ。",
        "transliterations": "かれ は いほう ちゅうしゃ で <b>ばっせられた</b> ん だ。",
        "meaning": "He was penalized for illegal parking.",
        "sound": "https://assets1.iknow.jp/assets/legacy/JLL/audio/Int/JS03380A.mp3"
      }
    ]
  },
  {
    "word": {
      "text": "清書",
      "transliterations": "せいしょ",
      "part_of_speech": "Verbal Noun",
      "meaning": "clean copy, final copy",
      "sound": "https://assets3.iknow.jp/assets/legacy/JLL/audio/Int/JW03689A.mp3"
    },
    "sentences": [
      {
        "text": "この手紙を<b>清書</b>してください。",
        "transliterations": "この てがみ を <b>せいしょ</b> して ください。",
        "meaning": "Please write a final copy of this letter.",
        "sound": "https://assets1.iknow.jp/assets/legacy/JLL/audio/Int/JS03689A.mp3"
      }
    ]
  },
  {
    "word": {
      "text": "交わる",
      "transliterations": "まじわる",
      "part_of_speech": "Verb",
      "meaning": "mingle, socialize",
      "sound": "https://assets2.iknow.jp/assets/legacy/JLL/audio/Int/JW02400A.mp3"
    },
    "sentences": [
      {
        "text": "人と<b>交わって</b>、多くのことを学びました。",
        "transliterations": "ひと と <b>まじわって</b>、おおく の こと を まなびました。",
        "meaning": "I learned a lot of things by socializing with other people.",
        "sound": "https://assets0.iknow.jp/assets/legacy/JLL/audio/Int/JS02400A.mp3"
      }
    ]
  },
  {
    "word": {
      "text": "受け取り",
      "transliterations": "うけとり",
      "part_of_speech": "Noun",
      "meaning": "receipt",
      "sound": "https://assets0.iknow.jp/assets/legacy/JLL/audio/Int/JW02671A.mp3"
    },
    "sentences": [
      {
        "text": "<b>受け取り</b>に判こをお願いします。",
        "transliterations": "<b>うけとり</b> に はんこ を おねがいします。",
        "meaning": "Please stamp your seal on the receipt.",
        "sound": "https://assets2.iknow.jp/assets/legacy/JLL/audio/Int/JS02671A.mp3"
      }
    ]
  },
  {
    "word": {
      "text": "にわかに",
      "transliterations": "にわかに",
      "part_of_speech": "Adverb",
      "meaning": "rapidly, at once",
      "sound": "https://assets1.iknow.jp/assets/legacy/JLL/audio/Int/JW03993A.mp3"
    },
    "sentences": [
      {
        "text": "空が<b>にわかに</b>暗くなったな。",
        "transliterations": "そら が <b>にわか に</b> くらく なった な。",
        "meaning": "The sky got dark at once.",
        "sound": "https://assets3.iknow.jp/assets/legacy/JLL/audio/Int/JS03993A.mp3"
      }
    ]
  },
  {
    "word": {
      "text": "年月",
      "transliterations": "としつき",
      "part_of_speech": "Noun",
      "meaning": "time, years",
      "sound": "https://assets3.iknow.jp/assets/legacy/JLL/audio/Int/JW02832A.mp3"
    },
    "sentences": [
      {
        "text": "あれから長い<b>年月</b>が経ちました。",
        "transliterations": "あれ から ながい <b>としつき</b> が たちました。",
        "meaning": "It's been a long time since then.",
        "sound": "https://assets1.iknow.jp/assets/legacy/JLL/audio/Int/JS02832A.mp3"
      }
    ]
  },
  {
    "word": {
      "text": "都",
      "transliterations": "みやこ",
      "part_of_speech": "Noun",
      "meaning": "capital, city",
      "sound": "https://assets3.iknow.jp/assets/legacy/JLL/audio/Int/JW00752A.mp3"
    },
    "sentences": [
      {
        "text": "ミラノはファッションの<b>都</b>です。",
        "transliterations": "ミラノ は ファッション の <b>みやこ</b> です。",
        "meaning": "Milan is the capital of fashion.",
        "sound": "https://assets1.iknow.jp/assets/legacy/JLL/audio/Int/JS00752A.mp3"
      }
    ]
  },
  {
    "word": {
      "text": "方々",
      "transliterations": "ほうぼう",
      "part_of_speech": "Noun",
      "meaning": "all directions, everywhere",
      "sound": "https://assets2.iknow.jp/assets/legacy/JLL/audio/Int/JW01571A.mp3"
    },
    "sentences": [
      {
        "text": "彼の連絡先を<b>方々</b>に問い合わせたんだ。",
        "transliterations": "かれ の れんらく さき を <b>ほうぼう</b> に といあわせた ん だ。",
        "meaning": "I inquired everywhere for his contact information.",
        "sound": "https://assets0.iknow.jp/assets/legacy/JLL/audio/Int/JS01571A.mp3"
      }
    ]
  },
  {
    "word": {
      "text": "陸",
      "transliterations": "りく",
      "part_of_speech": "Noun",
      "meaning": "land, shore",
      "sound": "https://assets3.iknow.jp/assets/legacy/JLL/audio/Int/JW03959A.mp3"
    },
    "sentences": [
      {
        "text": "ウミガメが<b>陸</b>に上がってきたんだ。",
        "transliterations": "ウミガメ が <b>りく</b> に あがって きた ん だ。",
        "meaning": "The sea turtles came up to the land.",
        "sound": "https://assets1.iknow.jp/assets/legacy/JLL/audio/Int/JS03959A.mp3"
      }
    ]
  },
  {
    "word": {
      "text": "能",
      "transliterations": "のう",
      "part_of_speech": "Noun",
      "meaning": "ability, capability",
      "sound": "https://assets2.iknow.jp/assets/legacy/JLL/audio/Int/JW03809A.mp3"
    },
    "sentences": [
      {
        "text": "彼は勉強するしか<b>能</b>のない人間だね。",
        "transliterations": "かれ は べんきょう する しか <b>のう</b> の ない にんげん だ ね。",
        "meaning": "He's a kind of person who can do nothing but study.",
        "sound": "https://assets0.iknow.jp/assets/legacy/JLL/audio/Int/JS03809A.mp3"
      }
    ]
  },
  {
    "word": {
      "text": "固体",
      "transliterations": "こたい",
      "part_of_speech": "Noun",
      "meaning": "solid, solid matter",
      "sound": "https://assets0.iknow.jp/assets/legacy/JLL/audio/Int/JW01476A.mp3"
    },
    "sentences": [
      {
        "text": "氷は<b>固体</b>です。",
        "transliterations": "こおり は <b>こたい</b> です。",
        "meaning": "Ice is a solid.",
        "sound": "https://assets2.iknow.jp/assets/legacy/JLL/audio/Int/JS01476A.mp3"
      }
    ]
  },
  {
    "word": {
      "text": "半面",
      "transliterations": "はんめん",
      "part_of_speech": "Noun",
      "meaning": "half, one side",
      "sound": "https://assets0.iknow.jp/assets/legacy/JLL/audio/Int/JW01356A.mp3"
    },
    "sentences": [
      {
        "text": "テニスコートの<b>半面</b>を使って試合をしたの。",
        "transliterations": "テニス コート の <b>はんめん</b> を つかって しあい を した の。",
        "meaning": "We played tennis using one half of the court.",
        "sound": "https://assets2.iknow.jp/assets/legacy/JLL/audio/Int/JS01356A.mp3"
      }
    ]
  },
  {
    "word": {
      "text": "家主",
      "transliterations": "やぬし",
      "part_of_speech": "Noun",
      "meaning": "owner of a rented house",
      "sound": "https://assets0.iknow.jp/assets/legacy/JLL/audio/Int/JW03938A.mp3"
    },
    "sentences": [
      {
        "text": "<b>家主</b>は1階に住んでいます。",
        "transliterations": "<b>やぬし</b> は 1 かい に すんで います。",
        "meaning": "The owner of this rented house lives on the first floor.",
        "sound": "https://assets2.iknow.jp/assets/legacy/JLL/audio/Int/JS03938A.mp3"
      }
    ]
  },
  {
    "word": {
      "text": "著す",
      "transliterations": "あらわす",
      "part_of_speech": "Verb",
      "meaning": "write (a book)",
      "sound": "https://assets3.iknow.jp/assets/legacy/JLL/audio/Int/JW03521A.mp3"
    },
    "sentences": [
      {
        "text": "この本では自然の大切さがよく<b>著されて</b>いるよ。",
        "transliterations": "この ほん で は しぜん の たいせつさ が よく <b>あらわされて</b> いる よ。",
        "meaning": "The importance of nature is well written in this book.",
        "sound": "https://assets1.iknow.jp/assets/legacy/JLL/audio/Int/JS03521A.mp3"
      }
    ]
  },
  {
    "word": {
      "text": "乗り越し",
      "transliterations": "のりこし",
      "part_of_speech": "Verbal Noun",
      "meaning": "riding past one's stop",
      "sound": "https://assets3.iknow.jp/assets/legacy/JLL/audio/Int/JW03470A.mp3"
    },
    "sentences": [
      {
        "text": "<b>乗り越し</b>を機械で精算したの。",
        "transliterations": "<b>のりこし</b> を きかい で せいさん した の。",
        "meaning": "I paid the excess fare at the machine.",
        "sound": "https://assets1.iknow.jp/assets/legacy/JLL/audio/Int/JS03470A.mp3"
      }
    ]
  },
  {
    "word": {
      "text": "日の入り",
      "transliterations": "ひのいり",
      "part_of_speech": "Noun",
      "meaning": "sunset",
      "sound": "https://assets0.iknow.jp/assets/legacy/JLL/audio/Int/JW03385A.mp3"
    },
    "sentences": [
      {
        "text": "今日の<b>日の入り</b>は午後6時でした。",
        "transliterations": "きょう の <b>ひのいり</b> は ごご 6 じ でした。",
        "meaning": "The sun set at 6 p.m. today.",
        "sound": "https://assets2.iknow.jp/assets/legacy/JLL/audio/Int/JS03385A.mp3"
      }
    ]
  },
  {
    "word": {
      "text": "単数",
      "transliterations": "たんすう",
      "part_of_speech": "Noun",
      "meaning": "singular",
      "sound": "https://assets1.iknow.jp/assets/legacy/JLL/audio/Int/JW03365A.mp3"
    },
    "sentences": [
      {
        "text": "penは<b>単数</b>でpensは複数です。",
        "transliterations": "pen は <b>たんすう</b> で pens は ふくすう です。",
        "meaning": "\"Pen\" is the singular and \"pens\" is the plural.",
        "sound": "https://assets3.iknow.jp/assets/legacy/JLL/audio/Int/JS03365A.mp3"
      }
    ]
  },
  {
    "word": {
      "text": "エチケット",
      "transliterations": "エチケット",
      "part_of_speech": "Noun",
      "meaning": "etiquette (loan word)",
      "sound": "https://assets0.iknow.jp/assets/legacy/JLL/audio/Int/JW03338A.mp3"
    },
    "sentences": [
      {
        "text": "<b>エチケット</b>を守ることは大切です。",
        "transliterations": "<b>エチケット</b> を まもる こと は たいせつ です。",
        "meaning": "It's important to keep the rules of etiquette.",
        "sound": "https://assets2.iknow.jp/assets/legacy/JLL/audio/Int/JS03338A.mp3"
      }
    ]
  },
  {
    "word": {
      "text": "大層",
      "transliterations": "たいそう",
      "part_of_speech": "Adverb",
      "meaning": "greatly, exceedingly",
      "sound": "https://assets1.iknow.jp/assets/legacy/JLL/audio/Int/JW03297A.mp3"
    },
    "sentences": [
      {
        "text": "彼は<b>大層</b>喜んでいました。",
        "transliterations": "かれ は <b>たいそう</b> よろこんで いました。",
        "meaning": "He was greatly pleased.",
        "sound": "https://assets3.iknow.jp/assets/legacy/JLL/audio/Int/JS03297A.mp3"
      }
    ]
  },
  {
    "word": {
      "text": "腰掛け",
      "transliterations": "こしかけ",
      "part_of_speech": "Noun",
      "meaning": "stool, seat (literary)",
      "sound": "https://assets0.iknow.jp/assets/legacy/JLL/audio/Int/JW03286A.mp3"
    },
    "sentences": [
      {
        "text": "<b>腰掛け</b>はありませんか。",
        "transliterations": "<b>こしかけ</b> は ありません か。",
        "meaning": "Do you have a stool?",
        "sound": "https://assets2.iknow.jp/assets/legacy/JLL/audio/Int/JS03286A.mp3"
      }
    ]
  },
  {
    "word": {
      "text": "客間",
      "transliterations": "きゃくま",
      "part_of_speech": "Noun",
      "meaning": "guest room",
      "sound": "https://assets3.iknow.jp/assets/legacy/JLL/audio/Int/JW03206A.mp3"
    },
    "sentences": [
      {
        "text": "お客さんを<b>客間</b>にお通ししたわよ。",
        "transliterations": "おきゃくさん を <b>きゃくま</b> に おとおしした わ よ。",
        "meaning": "I showed the guest into the reception room.",
        "sound": "https://assets1.iknow.jp/assets/legacy/JLL/audio/Int/JS03206A.mp3"
      }
    ]
  },
  {
    "word": {
      "text": "仮名遣い",
      "transliterations": "かなづかい",
      "part_of_speech": "Noun",
      "meaning": "kana orthography, use of kana",
      "sound": "https://assets3.iknow.jp/assets/legacy/JLL/audio/Int/JW03198A.mp3"
    },
    "sentences": [
      {
        "text": "祖父は古い<b>仮名遣い</b>で書くことがあるの。",
        "transliterations": "そふ は ふるい <b>かなづかい</b> で かく こと が ある の。",
        "meaning": "My grandfather sometimes uses the old kana orthography in writing.",
        "sound": "https://assets1.iknow.jp/assets/legacy/JLL/audio/Int/JS03198A.mp3"
      }
    ]
  },
  {
    "word": {
      "text": "温帯",
      "transliterations": "おんたい",
      "part_of_speech": "Noun",
      "meaning": "temperate zone",
      "sound": "https://assets0.iknow.jp/assets/legacy/JLL/audio/Int/JW03194A.mp3"
    },
    "sentences": [
      {
        "text": "日本は<b>温帯</b>にあります。",
        "transliterations": "にっぽん は <b>おんたい</b> に あります。",
        "meaning": "Japan is located in the temperate zone.",
        "sound": "https://assets2.iknow.jp/assets/legacy/JLL/audio/Int/JS03194A.mp3"
      }
    ]
  },
  {
    "word": {
      "text": "小数",
      "transliterations": "しょうすう",
      "part_of_speech": "Noun",
      "meaning": "decimal",
      "sound": "https://assets0.iknow.jp/assets/legacy/JLL/audio/Int/JW03144A.mp3"
    },
    "sentences": [
      {
        "text": "<b>小数</b>は切り捨てて計算してください。",
        "transliterations": "<b>しょうすう</b> は きりすてて けいさん して ください。",
        "meaning": "Please truncate the decimal when you calculate.",
        "sound": "https://assets2.iknow.jp/assets/legacy/JLL/audio/Int/JS03144A.mp3"
      }
    ]
  },
  {
    "word": {
      "text": "熱する",
      "transliterations": "ねっする",
      "part_of_speech": "Verb",
      "meaning": "heat (something)",
      "sound": "https://assets2.iknow.jp/assets/legacy/JLL/audio/Int/JW03044A.mp3"
    },
    "sentences": [
      {
        "text": "鉄は<b>熱する</b>と曲がるんだ。",
        "transliterations": "てつ は <b>ねっする</b> と まがる ん だ。",
        "meaning": "Iron bends when heated.",
        "sound": "https://assets0.iknow.jp/assets/legacy/JLL/audio/Int/JS03044A.mp3"
      }
    ]
  },
  {
    "word": {
      "text": "腰掛ける",
      "transliterations": "こしかける",
      "part_of_speech": "Verb",
      "meaning": "sit down (literary)",
      "sound": "https://assets2.iknow.jp/assets/legacy/JLL/audio/Int/JW02972A.mp3"
    },
    "sentences": [
      {
        "text": "私はベンチに<b>腰掛けた</b>の。",
        "transliterations": "わたし は ベンチ に <b>こしかけた</b> の。",
        "meaning": "I sat down on the bench.",
        "sound": "https://assets0.iknow.jp/assets/legacy/JLL/audio/Int/JS02972A.mp3"
      }
    ]
  },
  {
    "word": {
      "text": "盆地",
      "transliterations": "ぼんち",
      "part_of_speech": "Noun",
      "meaning": "basin",
      "sound": "https://assets0.iknow.jp/assets/legacy/JLL/audio/Int/JW02947A.mp3"
    },
    "sentences": [
      {
        "text": "<b>盆地</b>は夏、とても暑いんだ。",
        "transliterations": "<b>ぼんち</b> は なつ、とても あつい ん だ。",
        "meaning": "It's very hot in the basin during summer.",
        "sound": "https://assets2.iknow.jp/assets/legacy/JLL/audio/Int/JS02947A.mp3"
      }
    ]
  },
  {
    "word": {
      "text": "並木",
      "transliterations": "なみき",
      "part_of_speech": "Noun",
      "meaning": "row (line) of trees",
      "sound": "https://assets2.iknow.jp/assets/legacy/JLL/audio/Int/JW02492A.mp3"
    },
    "sentences": [
      {
        "text": "駅前の<b>並木</b>が台風で倒れたらしい。",
        "transliterations": "えき まえ の <b>なみき</b> が たいふう で たおれた らしい。",
        "meaning": "I heard that the line of trees in front of the station fell over in the typhoon.",
        "sound": "https://assets0.iknow.jp/assets/legacy/JLL/audio/Int/JS02492A.mp3"
      }
    ]
  },
  {
    "word": {
      "text": "材木",
      "transliterations": "ざいもく",
      "part_of_speech": "Noun",
      "meaning": "timber, wood",
      "sound": "https://assets1.iknow.jp/assets/legacy/JLL/audio/Int/JW02351A.mp3"
    },
    "sentences": [
      {
        "text": "船から<b>材木</b>が降ろされていますね。",
        "transliterations": "ふね から <b>ざいもく</b> が おろされて います ね。",
        "meaning": "Timber is being unloaded from the ship.",
        "sound": "https://assets3.iknow.jp/assets/legacy/JLL/audio/Int/JS02351A.mp3"
      }
    ]
  },
  {
    "word": {
      "text": "元日",
      "transliterations": "がんじつ",
      "part_of_speech": "Noun",
      "meaning": "New Year's Day",
      "sound": "https://assets3.iknow.jp/assets/legacy/JLL/audio/Int/JW02267A.mp3"
    },
    "sentences": [
      {
        "text": "<b>元日</b>には初詣に行きます。",
        "transliterations": "<b>がんじつ</b>  に は はつもうで に いきます。",
        "meaning": "I pay my first visit of the year to a shrine on New Year's Day.",
        "sound": "https://assets1.iknow.jp/assets/legacy/JLL/audio/Int/JS02267A.mp3"
      }
    ]
  },
  {
    "word": {
      "text": "たく",
      "transliterations": "たく",
      "part_of_speech": "Verb",
      "meaning": "make (a fire)",
      "sound": "https://assets1.iknow.jp/assets/legacy/JLL/audio/JW05308A.mp3"
    },
    "sentences": [
      {
        "text": "薪を集めて火を<b>たいた</b>よ。",
        "transliterations": "まき を あつめて ひ を <b>たいた</b> よ。",
        "meaning": "I gathered wood and made a fire.",
        "sound": "https://assets3.iknow.jp/assets/legacy/JLL/audio/Int/JS02245A.mp3"
      }
    ]
  },
  {
    "word": {
      "text": "照る",
      "transliterations": "てる",
      "part_of_speech": "Verb",
      "meaning": "shine, blaze",
      "sound": "https://assets0.iknow.jp/assets/legacy/JLL/audio/Int/JW02218A.mp3"
    },
    "sentences": [
      {
        "text": "日差しが強く<b>照り</b>つけますね。",
        "transliterations": "ひざし が つよく <b>てり</b>つけます ね。",
        "meaning": "The sun is blazing strongly.",
        "sound": "https://assets2.iknow.jp/assets/legacy/JLL/audio/Int/JS02218A.mp3"
      }
    ]
  },
  {
    "word": {
      "text": "気体",
      "transliterations": "きたい",
      "part_of_speech": "Noun",
      "meaning": "gaseous body, gas",
      "sound": "https://assets0.iknow.jp/assets/legacy/JLL/audio/Int/JW01187A.mp3"
    },
    "sentences": [
      {
        "text": "水が沸騰して<b>気体</b>になったんだ。",
        "transliterations": "みず が ふっとう して <b>きたい</b> に なった ん だ。",
        "meaning": "The water boiled and turned into a gaseous body.",
        "sound": "https://assets2.iknow.jp/assets/legacy/JLL/audio/Int/JS01187A.mp3"
      }
    ]
  },
  {
    "word": {
      "text": "和英",
      "transliterations": "わえい",
      "part_of_speech": "Noun",
      "meaning": "Japanese-English",
      "sound": "https://assets0.iknow.jp/assets/legacy/JLL/audio/Int/JW03502A.mp3"
    },
    "sentences": [
      {
        "text": "私は<b>和英</b>辞書をよく使います。",
        "transliterations": "わたし は <b>わえい</b> じしょ を よく つかいます。",
        "meaning": "I often use a Japanese-English dictionary.",
        "sound": "https://assets2.iknow.jp/assets/legacy/JLL/audio/Int/JS03502A.mp3"
      }
    ]
  },
  {
    "word": {
      "text": "支援",
      "transliterations": "しえん",
      "part_of_speech": "Verbal Noun",
      "meaning": "support, backing",
      "sound": "https://assets3.iknow.jp/assets/legacy/JLL/audio/Int/JW00072A.mp3"
    },
    "sentences": [
      {
        "text": "彼の<b>支援</b>がなかったらどうなっていたか。",
        "transliterations": "かれ の <b>しえん</b> が なかったら どう なって いた か。",
        "meaning": "What would have happened without his support?",
        "sound": "https://assets1.iknow.jp/assets/legacy/JLL/audio/Int/JS00072A.mp3"
      }
    ]
  },
  {
    "word": {
      "text": "思い",
      "transliterations": "おもい",
      "part_of_speech": "Noun",
      "meaning": "thoughts, feelings",
      "sound": "https://assets3.iknow.jp/assets/legacy/JLL/audio/Int/JW00313A.mp3"
    },
    "sentences": [
      {
        "text": "必死の<b>思い</b>で彼に頼んだよ。",
        "transliterations": "ひっし の <b>おもい</b> で かれ に たのんだ よ。",
        "meaning": "I desperately asked him for help.",
        "sound": "https://assets1.iknow.jp/assets/legacy/JLL/audio/Int/JS00313A.mp3"
      }
    ]
  },
  {
    "word": {
      "text": "日々",
      "transliterations": "ひび",
      "part_of_speech": "Noun",
      "meaning": "daily, every day",
      "sound": "https://assets1.iknow.jp/assets/legacy/JLL/audio/Int/JW03849A.mp3"
    },
    "sentences": [
      {
        "text": "<b>日々</b>の努力が大切です。",
        "transliterations": "<b>ひび</b> の どりょく が たいせつ です。",
        "meaning": "It's important to make day-to-day efforts.",
        "sound": "https://assets3.iknow.jp/assets/legacy/JLL/audio/Int/JS03849A.mp3"
      }
    ]
  },
  {
    "word": {
      "text": "せい",
      "transliterations": "せい",
      "part_of_speech": "Noun",
      "meaning": "cause, blame",
      "sound": "https://assets1.iknow.jp/assets/legacy/JLL/audio/Int/JW00270A.mp3"
    },
    "sentences": [
      {
        "text": "自分の失敗を他人の<b>せい</b>にするな。",
        "transliterations": "じぶん の しっぱい を たにん の <b>せい</b> に する な。",
        "meaning": "Don't blame others for your mistake.",
        "sound": "https://assets3.iknow.jp/assets/legacy/JLL/audio/Int/JS00270A.mp3"
      }
    ]
  },
  {
    "word": {
      "text": "距離",
      "transliterations": "きょり",
      "part_of_speech": "Noun",
      "meaning": "distance",
      "sound": "https://assets0.iknow.jp/assets/legacy/JLL/audio/Int/JW00337A.mp3"
    },
    "sentences": [
      {
        "text": "彼らは長い<b>距離</b>を歩き続けたんだ。",
        "transliterations": "かれら は ながい <b>きょり</b> を あるき つづけた ん だ。",
        "meaning": "They kept walking a long distance.",
        "sound": "https://assets2.iknow.jp/assets/legacy/JLL/audio/Int/JS00337A.mp3"
      }
    ]
  },
  {
    "word": {
      "text": "仕組み",
      "transliterations": "しくみ",
      "part_of_speech": "Noun",
      "meaning": "construction, mechanism",
      "sound": "https://assets2.iknow.jp/assets/legacy/JLL/audio/Int/JW00555A.mp3"
    },
    "sentences": [
      {
        "text": "この機械の<b>仕組み</b>は複雑だ。",
        "transliterations": "この きかい の <b>しくみ</b> は ふくざつ だ。",
        "meaning": "The mechanism of this machine is complex.",
        "sound": "https://assets0.iknow.jp/assets/legacy/JLL/audio/Int/JS00555A.mp3"
      }
    ]
  },
  {
    "word": {
      "text": "お前",
      "transliterations": "おまえ",
      "part_of_speech": "Noun",
      "meaning": "you (vulgar language)",
      "sound": "https://assets0.iknow.jp/assets/legacy/JLL/audio/Int/JW02961A.mp3"
    },
    "sentences": [
      {
        "text": "<b>お前</b>の言うことは信じられない。",
        "transliterations": "<b>おまえ</b> の いう こと は しんじられない。",
        "meaning": "I can't believe what you say.",
        "sound": "https://assets2.iknow.jp/assets/legacy/JLL/audio/Int/JS02961A.mp3"
      }
    ]
  },
  {
    "word": {
      "text": "男女",
      "transliterations": "だんじょ",
      "part_of_speech": "Noun",
      "meaning": "men and women",
      "sound": "https://assets3.iknow.jp/assets/legacy/JLL/audio/Int/JW03716A.mp3"
    },
    "sentences": [
      {
        "text": "そのスポーツは<b>男女</b>一緒にします。",
        "transliterations": "その スポーツ は <b>だんじょ</b> いっしょ に します。",
        "meaning": "Men and women play that sport together.",
        "sound": "https://assets1.iknow.jp/assets/legacy/JLL/audio/Int/JS03716A.mp3"
      }
    ]
  },
  {
    "word": {
      "text": "役立つ",
      "transliterations": "やくだつ",
      "part_of_speech": "Verb",
      "meaning": "be of use, come in handy",
      "sound": "https://assets0.iknow.jp/assets/legacy/JLL/audio/Int/JW00577A.mp3"
    },
    "sentences": [
      {
        "text": "学校で勉強したことが<b>役立った</b>。",
        "transliterations": "がっこう で べんきょう した こと が <b>やくだった</b>。",
        "meaning": "What I learned at school turned out to be useful.",
        "sound": "https://assets2.iknow.jp/assets/legacy/JLL/audio/Int/JS00577A.mp3"
      }
    ]
  },
  {
    "word": {
      "text": "ロック",
      "transliterations": "ロック",
      "part_of_speech": "Noun",
      "meaning": "rock (music)",
      "sound": "https://assets3.iknow.jp/assets/legacy/JLL/audio/Int/JW01301A.mp3"
    },
    "sentences": [
      {
        "text": "俺は<b>ロック</b>を聞くのが好きだ。",
        "transliterations": "おれ は <b>ロック</b> を きく の が すき だ。",
        "meaning": "I like to listen to rock music.",
        "sound": "https://assets1.iknow.jp/assets/legacy/JLL/audio/Int/JS01301A.mp3"
      }
    ]
  },
  {
    "word": {
      "text": "市内",
      "transliterations": "しない",
      "part_of_speech": "Noun",
      "meaning": "in the city",
      "sound": "https://assets3.iknow.jp/assets/legacy/JLL/audio/Int/JW00093A.mp3"
    },
    "sentences": [
      {
        "text": "明日は<b>市内</b>を観光する予定です。",
        "transliterations": "あした は <b>しない</b> を かんこう する よてい です。",
        "meaning": "I'm planning go sightseeing in the city tomorrow.",
        "sound": "https://assets1.iknow.jp/assets/legacy/JLL/audio/Int/JS00093A.mp3"
      }
    ]
  },
  {
    "word": {
      "text": "我が家",
      "transliterations": "わがや",
      "part_of_speech": "Noun",
      "meaning": "one's home",
      "sound": "https://assets2.iknow.jp/assets/legacy/JLL/audio/Int/JW03062A.mp3"
    },
    "sentences": [
      {
        "text": "ぜひ<b>我が家</b>に遊びに来てください。",
        "transliterations": "ぜひ <b>わがや</b> に あそび に きて ください。",
        "meaning": "Please come and visit us at home.",
        "sound": "https://assets0.iknow.jp/assets/legacy/JLL/audio/Int/JS03062A.mp3"
      }
    ]
  },
  {
    "word": {
      "text": "浮かぶ",
      "transliterations": "うかぶ",
      "part_of_speech": "Verb",
      "meaning": "float (on a surface)",
      "sound": "https://assets1.iknow.jp/assets/legacy/JLL/audio/Int/JW00374A.mp3"
    },
    "sentences": [
      {
        "text": "沖にボートが<b>浮かんで</b>います。",
        "transliterations": "おき に ボート が <b>うかんで</b> います。",
        "meaning": "The boat is floating off the coast.",
        "sound": "https://assets3.iknow.jp/assets/legacy/JLL/audio/Int/JS00374A.mp3"
      }
    ]
  },
  {
    "word": {
      "text": "生み出す",
      "transliterations": "うみだす",
      "part_of_speech": "Verb",
      "meaning": "generate, produce",
      "sound": "https://assets1.iknow.jp/assets/legacy/JLL/audio/Int/JW01017A.mp3"
    },
    "sentences": [
      {
        "text": "彼は数々の名作を<b>生み出した</b>。",
        "transliterations": "かれ は かずかず の めいさく を <b>うみだした</b>。",
        "meaning": "He produced a number of masterpieces.",
        "sound": "https://assets3.iknow.jp/assets/legacy/JLL/audio/Int/JS01017A.mp3"
      }
    ]
  },
  {
    "word": {
      "text": "たった",
      "transliterations": "たった",
      "part_of_speech": "Adverb",
      "meaning": "only, merely",
      "sound": "https://assets1.iknow.jp/assets/legacy/JLL/audio/Int/JW01701A.mp3"
    },
    "sentences": [
      {
        "text": "財布の中に<b>たった</b>1000円しかないよ。",
        "transliterations": "さいふ の なか に <b>たった</b> 1000 えん しか ない よ。",
        "meaning": "I only have 1,000 yen in my wallet.",
        "sound": "https://assets3.iknow.jp/assets/legacy/JLL/audio/Int/JS01701A.mp3"
      }
    ]
  },
  {
    "word": {
      "text": "キリスト",
      "transliterations": "キリスト",
      "part_of_speech": "Noun",
      "meaning": "Christ",
      "sound": "https://assets0.iknow.jp/assets/legacy/JLL/audio/Int/JW01958A.mp3"
    },
    "sentences": [
      {
        "text": "<b>キリスト</b>の母親の名前はマリアだ。",
        "transliterations": "<b>キリスト</b> の ははおや の なまえ は マリア だ。",
        "meaning": "The name of Christ's mother is Maria.",
        "sound": "https://assets2.iknow.jp/assets/legacy/JLL/audio/Int/JS01958A.mp3"
      }
    ]
  },
  {
    "word": {
      "text": "あえて",
      "transliterations": "あえて",
      "part_of_speech": "Adverb",
      "meaning": "dare, boldly",
      "sound": "https://assets1.iknow.jp/assets/legacy/JLL/audio/Int/JW01302A.mp3"
    },
    "sentences": [
      {
        "text": "彼は<b>あえて</b>危険を冒したの。",
        "transliterations": "かれ は <b>あえて</b> きけん を おかした の。",
        "meaning": "He dared to face danger.",
        "sound": "https://assets3.iknow.jp/assets/legacy/JLL/audio/Int/JS01302A.mp3"
      }
    ]
  },
  {
    "word": {
      "text": "抑える",
      "transliterations": "おさえる",
      "part_of_speech": "Verb",
      "meaning": "suppress, bring under control",
      "sound": "https://assets3.iknow.jp/assets/legacy/JLL/audio/Int/JW00440A.mp3"
    },
    "sentences": [
      {
        "text": "彼は怒りを<b>抑えて</b>いたの。",
        "transliterations": "かれ は いかり を <b>おさえて</b> いた の。",
        "meaning": "He was suppressing his anger.",
        "sound": "https://assets1.iknow.jp/assets/legacy/JLL/audio/Int/JS00440A.mp3"
      }
    ]
  },
  {
    "word": {
      "text": "見つめる",
      "transliterations": "みつめる",
      "part_of_speech": "Verb",
      "meaning": "stare, gaze",
      "sound": "https://assets3.iknow.jp/assets/legacy/JLL/audio/Int/JW02846A.mp3"
    },
    "sentences": [
      {
        "text": "彼はその絵をずっと<b>見つめて</b>いたの。",
        "transliterations": "かれ は その え を ずっと <b>みつめて</b> いた の。",
        "meaning": "He was staring at the painting for a long time.",
        "sound": "https://assets1.iknow.jp/assets/legacy/JLL/audio/Int/JS02846A.mp3"
      }
    ]
  },
  {
    "word": {
      "text": "ハード",
      "transliterations": "ハード",
      "part_of_speech": "Adjectival Noun",
      "meaning": "hard",
      "sound": "https://assets2.iknow.jp/assets/legacy/JLL/audio/Int/JW00966A.mp3"
    },
    "sentences": [
      {
        "text": "最近、仕事がかなり<b>ハード</b>です。",
        "transliterations": "さいきん、しごと が かなり <b>ハード</b> です。",
        "meaning": "My work is pretty hard these days.",
        "sound": "https://assets0.iknow.jp/assets/legacy/JLL/audio/Int/JS00966A.mp3"
      }
    ]
  },
  {
    "word": {
      "text": "幅広い",
      "transliterations": "はばひろい",
      "part_of_speech": "Adjective",
      "meaning": "wide, profound",
      "sound": "https://assets2.iknow.jp/assets/legacy/JLL/audio/Int/JW00718A.mp3"
    },
    "sentences": [
      {
        "text": "彼は<b>幅広い</b>知識を持っています。",
        "transliterations": "かれ は <b>はばひろい</b> ちしき を もって います。",
        "meaning": "He has profound knowledge.",
        "sound": "https://assets0.iknow.jp/assets/legacy/JLL/audio/Int/JS00718A.mp3"
      }
    ]
  },
  {
    "word": {
      "text": "つなぐ",
      "transliterations": "つなぐ",
      "part_of_speech": "Verb",
      "meaning": "connect (someone, something)",
      "sound": "https://assets0.iknow.jp/assets/legacy/JLL/audio/Int/JW03746A.mp3"
    },
    "sentences": [
      {
        "text": "インターネットは世界の人々を<b>つなぎます</b>ね。",
        "transliterations": "インターネット は せかい の ひとびと を <b>つなぎます</b> ね。",
        "meaning": "The Internet connects people all around the world.",
        "sound": "https://assets2.iknow.jp/assets/legacy/JLL/audio/Int/JS03746A.mp3"
      }
    ]
  },
  {
    "word": {
      "text": "申し込み",
      "transliterations": "もうしこみ",
      "part_of_speech": "Noun",
      "meaning": "application, signing up",
      "sound": "https://assets0.iknow.jp/assets/legacy/JLL/audio/Int/JW01150A.mp3"
    },
    "sentences": [
      {
        "text": "今日、スポーツジムの<b>申し込み</b>をしました。",
        "transliterations": "きょう、スポーツジム の <b>もうしこみ</b> を しました。",
        "meaning": "I signed up for a sports gym today.",
        "sound": "https://assets2.iknow.jp/assets/legacy/JLL/audio/Int/JS01150A.mp3"
      }
    ]
  },
  {
    "word": {
      "text": "向き",
      "transliterations": "むき",
      "part_of_speech": "Noun",
      "meaning": "direction, turn",
      "sound": "https://assets2.iknow.jp/assets/legacy/JLL/audio/Int/JW01260A.mp3"
    },
    "sentences": [
      {
        "text": "花瓶の<b>向き</b>を変えたの。",
        "transliterations": "かびん の <b>むき</b> を かえた の。",
        "meaning": "I turned the vase around.",
        "sound": "https://assets0.iknow.jp/assets/legacy/JLL/audio/Int/JS01260A.mp3"
      }
    ]
  },
  {
    "word": {
      "text": "持ち込む",
      "transliterations": "もちこむ",
      "part_of_speech": "Verb",
      "meaning": "bring in, carry on",
      "sound": "https://assets2.iknow.jp/assets/legacy/JLL/audio/Int/JW00634A.mp3"
    },
    "sentences": [
      {
        "text": "機内に荷物を<b>持ち込んだ</b>の。",
        "transliterations": "きない に にもつ を <b>もちこんだ</b> の。",
        "meaning": "I carried my luggage onto the plane.",
        "sound": "https://assets0.iknow.jp/assets/legacy/JLL/audio/Int/JS00634A.mp3"
      }
    ]
  },
  {
    "word": {
      "text": "徹底的",
      "transliterations": "てっていてき",
      "part_of_speech": "Adjectival Noun",
      "meaning": "thorough",
      "sound": "https://assets2.iknow.jp/assets/legacy/JLL/audio/Int/JW01392A.mp3"
    },
    "sentences": [
      {
        "text": "部屋の中を<b>徹底的</b>に探しました。",
        "transliterations": "へや の なか を <b>てっていてき</b> に さがしました。",
        "meaning": "I searched inside the room thoroughly.",
        "sound": "https://assets0.iknow.jp/assets/legacy/JLL/audio/Int/JS01392A.mp3"
      }
    ]
  },
  {
    "word": {
      "text": "前向き",
      "transliterations": "まえむき",
      "part_of_speech": "Adjectival Noun",
      "meaning": "facing forward, positive",
      "sound": "https://assets0.iknow.jp/assets/legacy/JLL/audio/Int/JW01738A.mp3"
    },
    "sentences": [
      {
        "text": "<b>前向き</b>に検討します。",
        "transliterations": "<b>まえむき</b> に けんとう します。",
        "meaning": "We'll consider the matter positively.",
        "sound": "https://assets2.iknow.jp/assets/legacy/JLL/audio/Int/JS01738A.mp3"
      }
    ]
  },
  {
    "word": {
      "text": "録画",
      "transliterations": "ろくが",
      "part_of_speech": "Verbal Noun",
      "meaning": "videotaping, recording",
      "sound": "https://assets0.iknow.jp/assets/legacy/JLL/audio/Int/JW02794A.mp3"
    },
    "sentences": [
      {
        "text": "好きな番組を<b>録画</b>したの。",
        "transliterations": "すきな ばんぐみ を <b>ろくが</b> した の。",
        "meaning": "I recorded my favorite program.",
        "sound": "https://assets2.iknow.jp/assets/legacy/JLL/audio/Int/JS02794A.mp3"
      }
    ]
  },
  {
    "word": {
      "text": "喫煙",
      "transliterations": "きつえん",
      "part_of_speech": "Verbal Noun",
      "meaning": "smoking",
      "sound": "https://assets2.iknow.jp/assets/legacy/JLL/audio/Int/JW01673A.mp3"
    },
    "sentences": [
      {
        "text": "ここでは<b>喫煙</b>できません。",
        "transliterations": "ここ で は <b>きつえん</b> できません。",
        "meaning": "Smoking is not permitted here.",
        "sound": "https://assets0.iknow.jp/assets/legacy/JLL/audio/Int/JS01673A.mp3"
      }
    ]
  },
  {
    "word": {
      "text": "乗り越える",
      "transliterations": "のりこえる",
      "part_of_speech": "Verb",
      "meaning": "overcome, get over",
      "sound": "https://assets3.iknow.jp/assets/legacy/JLL/audio/Int/JW01569A.mp3"
    },
    "sentences": [
      {
        "text": "彼は悲しみを<b>乗り越えて</b>強く生きた。",
        "transliterations": "かれ は かなしみ を <b>のりこえて</b> つよく いきた。",
        "meaning": "He overcame his sadness and carried on with his life determinedly.",
        "sound": "https://assets1.iknow.jp/assets/legacy/JLL/audio/Int/JS01569A.mp3"
      }
    ]
  },
  {
    "word": {
      "text": "値上げ",
      "transliterations": "ねあげ",
      "part_of_speech": "Verbal Noun",
      "meaning": "price hike, price increase",
      "sound": "https://assets1.iknow.jp/assets/legacy/JLL/audio/Int/JW00748A.mp3"
    },
    "sentences": [
      {
        "text": "バス代が<b>値上げ</b>されました。",
        "transliterations": "バス だい が <b>ねあげ</b> されました。",
        "meaning": "Bus fares have been increased.",
        "sound": "https://assets3.iknow.jp/assets/legacy/JLL/audio/Int/JS00748A.mp3"
      }
    ]
  },
  {
    "word": {
      "text": "まし",
      "transliterations": "まし",
      "part_of_speech": "Adjectival Noun",
      "meaning": "better, preferable",
      "sound": "https://assets2.iknow.jp/assets/legacy/JLL/audio/Int/JW02787A.mp3"
    },
    "sentences": [
      {
        "text": "これでもないより<b>まし</b>だ。",
        "transliterations": "これ で も ない より <b>まし</b> だ。",
        "meaning": "Even this is better than nothing.",
        "sound": "https://assets0.iknow.jp/assets/legacy/JLL/audio/Int/JS02787A.mp3"
      }
    ]
  },
  {
    "word": {
      "text": "なぜか",
      "transliterations": "なぜか",
      "part_of_speech": "Adverb",
      "meaning": "for no reason",
      "sound": "https://assets3.iknow.jp/assets/legacy/JLL/audio/Int/JW03990A.mp3"
    },
    "sentences": [
      {
        "text": "今日は<b>なぜか</b>体がだるい。",
        "transliterations": "きょう は <b>なぜ か</b> からだ が だるい。",
        "meaning": "For no reason I feel heavy today.",
        "sound": "https://assets1.iknow.jp/assets/legacy/JLL/audio/Int/JS03990A.mp3"
      }
    ]
  },
  {
    "word": {
      "text": "欲",
      "transliterations": "よく",
      "part_of_speech": "Noun",
      "meaning": "desire, greed",
      "sound": "https://assets1.iknow.jp/assets/legacy/JLL/audio/Int/JW02341A.mp3"
    },
    "sentences": [
      {
        "text": "あまり<b>欲</b>を出しちゃだめだよ。",
        "transliterations": "あまり <b>よく</b> を だしちゃ だめ だ よ。",
        "meaning": "Don't be too greedy.",
        "sound": "https://assets3.iknow.jp/assets/legacy/JLL/audio/Int/JS02341A.mp3"
      }
    ]
  },
  {
    "word": {
      "text": "守備",
      "transliterations": "しゅび",
      "part_of_speech": "Verbal Noun",
      "meaning": "defense, fielding",
      "sound": "https://assets2.iknow.jp/assets/legacy/JLL/audio/Int/JW02240A.mp3"
    },
    "sentences": [
      {
        "text": "そのチームは<b>守備</b>が甘いね。",
        "transliterations": "その チーム は <b>しゅび</b> が あまい ね。",
        "meaning": "The team's defense is weak.",
        "sound": "https://assets0.iknow.jp/assets/legacy/JLL/audio/Int/JS02240A.mp3"
      }
    ]
  }
]
